rosahami_processor/__init__.py
rosahami_processor-1.0.5.dist-info/LICENSE
rosahami_processor-1.0.5.dist-info/METADATA
rosahami_processor-1.0.5.dist-info/WHEEL
rosahami_processor-1.0.5.dist-info/top_level.txt
rosahami_processor-1.0.5.dist-info/RECORD
