Metadata-Version: 2.1
Name: rosahami-processor
Version: 1.0.5
Summary: tool to process SAXS data measured by using the HAPG SAXS mirror
Home-page: https://gitlab.hzdr.de/smid55/rosahami_processor
Author: Michal Smid
Author-email: m.smid@hzdr.de
License: UNKNOWN
Platform: UNKNOWN
Classifier: Programming Language :: Python :: 3
Classifier: License :: OSI Approved :: MIT License
Classifier: Operating System :: OS Independent
Requires-Python: >=3.6
License-File: LICENSE
